{"/_app":"pages/_app.js","/_error":"pages/_error.js","/alphabet":"pages/alphabet.html","/daily-review":"pages/daily-review.html","/games":"pages/games.html","/":"pages/index.html","/interactive-stories":"pages/interactive-stories.html","/parent-report":"pages/parent-report.html","/progress":"pages/progress.html","/quiz":"pages/quiz.html","/quran-memorization":"pages/quran-memorization.html","/quran-stories":"pages/quran-stories.html","/rewards":"pages/rewards.html","/vocabulary":"pages/vocabulary.html","/_document":"pages/_document.js","/404":"pages/404.html"}